pypnnomenclature/__init__.py
pypnnomenclature/admin.py
pypnnomenclature/env.py
pypnnomenclature/models.py
pypnnomenclature/repository.py
pypnnomenclature/routes.py
pypnnomenclature/schemas.py
pypnnomenclature/test_settings.py
pypnnomenclature/utils.py
pypnnomenclature/migrations/__init__.py
pypnnomenclature/migrations/env.py
pypnnomenclature/migrations/data/__init__.py
pypnnomenclature/migrations/data/nomenclatures.sql
pypnnomenclature/migrations/data/nomenclatures_inpn_data.sql
pypnnomenclature/migrations/data/nomenclatures_taxonomie.sql
pypnnomenclature/migrations/data/nomenclatures_taxonomie_data.sql
pypnnomenclature/migrations/versions/11e7741319fd_get_default_nomenclature_value.py
pypnnomenclature/migrations/versions/5e882af04ff6_add_nomenclatures_for_occhab.py
pypnnomenclature/migrations/versions/6015397d686a_nomenclatures.py
pypnnomenclature/migrations/versions/618542880d1f_fix_typo_nomenc_type_def.py
pypnnomenclature/migrations/versions/803524258bd3_add_group3_inpn_cor_taxref.py
pypnnomenclature/migrations/versions/8eb9a12db289_add_type_sol.py
pypnnomenclature/migrations/versions/96a713739fdd_nomenclatures_inpn_data.py
pypnnomenclature/migrations/versions/__init__.py
pypnnomenclature/migrations/versions/a763fb554ff2_nomenclatures_taxonomie_data.py
pypnnomenclature/migrations/versions/b820c66d8daa_get_nomenclature_label.py
pypnnomenclature/migrations/versions/ee1146f6c0f4_add_uicn_rl.py
pypnnomenclature/migrations/versions/f5436084bf17_nomenclatures_taxonomie.py
pypnnomenclature/migrations/versions/f8c2c8482419_get_default_nomenclature_value.py
pypnnomenclature/tests/__init__.py
pypnnomenclature/tests/conftest.py
pypnnomenclature/tests/test_nomenclatures.py
pypnnomenclature-1.6.5.dist-info/licenses/LICENSE
pypnnomenclature-1.6.5.dist-info/METADATA
pypnnomenclature-1.6.5.dist-info/WHEEL
pypnnomenclature-1.6.5.dist-info/entry_points.txt
pypnnomenclature-1.6.5.dist-info/top_level.txt
pypnnomenclature-1.6.5.dist-info/RECORD
